rstcheck/__init__.py
rstcheck/__main__.py
rstcheck/__version__.py
rstcheck/_cli.py
rstcheck/py.typed
rstcheck-6.2.4.dist-info/AUTHORS.rst
rstcheck-6.2.4.dist-info/LICENSE
rstcheck-6.2.4.dist-info/METADATA
rstcheck-6.2.4.dist-info/WHEEL
rstcheck-6.2.4.dist-info/entry_points.txt
rstcheck-6.2.4.dist-info/top_level.txt
rstcheck-6.2.4.dist-info/RECORD
