Metadata-Version: 2.1
Name: rstcheck
Version: 6.2.4
Summary: Checks syntax of reStructuredText and code blocks nested within it
Author-email: Steven Myint <git@stevenmyint.com>
Maintainer-email: Christian Riedel <cielquan@protonmail.com>
License: MIT
Project-URL: Documentation, https://rstcheck.readthedocs.io/en/latest/
Project-URL: Repository, https://github.com/rstcheck/rstcheck
Project-URL: Changelog, https://github.com/rstcheck/rstcheck/blob/main/CHANGELOG.md
Keywords: restructuredtext,rst,linter,static-analysis
Classifier: Topic :: Software Development :: Quality Assurance
Requires-Python: >=3.8
License-File: LICENSE
License-File: AUTHORS.rst
Requires-Dist: rstcheck-core>=1.1
Requires-Dist: typer>=0.12.0
Provides-Extra: sphinx
Requires-Dist: sphinx>=5.0; extra == "sphinx"
Provides-Extra: toml
Requires-Dist: tomli>=2.0; python_version <= "3.10" and extra == "toml"
Provides-Extra: testing
Requires-Dist: pytest>=7.2; extra == "testing"
Requires-Dist: pytest-cov>=3.0; extra == "testing"
Requires-Dist: coverage[toml]>=6.0; extra == "testing"
Requires-Dist: coverage-conditional-plugin>=0.5; extra == "testing"
Requires-Dist: pytest-sugar>=0.9.5; extra == "testing"
Requires-Dist: pytest-randomly>=3.0; extra == "testing"
Provides-Extra: docs
Requires-Dist: sphinx>=5.0; extra == "docs"
Requires-Dist: myst-parser>=3; extra == "docs"
Requires-Dist: sphinx-rtd-theme>=1.2; extra == "docs"
Requires-Dist: sphinxcontrib-spelling>=7.3; extra == "docs"
Requires-Dist: sphinx-click>=4.0.3; extra == "docs"
Requires-Dist: sphinx-autobuild>=2021.3.14; extra == "docs"
Provides-Extra: type-check
Requires-Dist: mypy>=1.0; extra == "type-check"
Provides-Extra: dev
Requires-Dist: rstcheck[docs,sphinx,testing,toml,type-check]; extra == "dev"
Requires-Dist: tox>=3.15; extra == "dev"
